pyetherscan/__init__.py
pyetherscan/client.py
pyetherscan/error.py
pyetherscan/ethereum.py
pyetherscan/response.py
pyetherscan/settings.py
pyetherscan-0.1.2.dist-info/DESCRIPTION.rst
pyetherscan-0.1.2.dist-info/METADATA
pyetherscan-0.1.2.dist-info/RECORD
pyetherscan-0.1.2.dist-info/WHEEL
pyetherscan-0.1.2.dist-info/metadata.json
pyetherscan-0.1.2.dist-info/top_level.txt
