Metadata-Version: 2.0
Name: pyetherscan
Version: 0.1.2
Summary: An unofficial wrapper for the Etherscan.io API
Home-page: https://github.com/Marto32/pyetherscan
Author: Michael Martorella
Author-email: michaelmartorella@gmail.com
License: MIT License
Download-URL: https://github.com/Marto32/pyetherscan/archive/0.1.2.tar.gz
Keywords: ethereum,blockchain,etherscan
Platform: UNKNOWN
Classifier: Development Status :: 3 - Alpha
Classifier: Intended Audience :: Developers
Classifier: License :: OSI Approved :: MIT License
Classifier: Natural Language :: English
Classifier: Programming Language :: Python :: 2.7
Classifier: Programming Language :: Python :: 3.3
Classifier: Programming Language :: Python :: 3.4
Classifier: Programming Language :: Python :: 3.5
Classifier: Programming Language :: Python :: 3.6
Requires-Dist: requests
Requires-Dist: retrying
